codern/Client.py
codern/__init__.py
codern-4.4.9.dist-info/METADATA
codern-4.4.9.dist-info/WHEEL
codern-4.4.9.dist-info/top_level.txt
codern-4.4.9.dist-info/RECORD
