Metadata-Version: 2.1
Name: codern
Version: 4.4.9
Summary: Codern Team Library from api free O - > api-free.ir
Home-page: https://api-free.ir
Author: Mahdi Ahmadi
Author-email: mahdiahmadi.1208@gmail.com
Classifier: Programming Language :: Python :: 3
Classifier: License :: OSI Approved :: MIT License
Classifier: Operating System :: OS Independent
Requires-Python: >=3.6
Requires-Dist: requests
Requires-Dist: httpx
Requires-Dist: bs4
Requires-Dist: urllib3
Requires-Dist: pycryptodome
Requires-Dist: pillow
